mapclassify/__init__.py
mapclassify/_classify_API.py
mapclassify/_version.py
mapclassify/classifiers.py
mapclassify/greedy.py
mapclassify/pooling.py
mapclassify/datasets/__init__.py
mapclassify/datasets/calemp/__init__.py
mapclassify/datasets/calemp/calempdensity.csv
mapclassify/datasets/calemp/data.py
mapclassify/tests/__init__.py
mapclassify/tests/test_classify.py
mapclassify/tests/test_greedy.py
mapclassify/tests/test_mapclassify.py
mapclassify-23.1.dist-info/LICENSE.txt
mapclassify-23.1.dist-info/METADATA
mapclassify-23.1.dist-info/WHEEL
mapclassify-23.1.dist-info/top_level.txt
mapclassify-23.1.dist-info/RECORD
