Metadata-Version: 2.1
Name: mapclassify
Version: 23.1
Summary: Classification Schemes for Choropleth Maps.
Home-page: https://github.com/pysal/mapclassify
Maintainer: Serge Rey, Wei Kang
Maintainer-email: sjsrey@gmail.com, weikang9009@gmail.com
License: 3-Clause BSD
Keywords: spatial statistics,geovisualizaiton
Classifier: Development Status :: 5 - Production/Stable
Classifier: Intended Audience :: Science/Research
Classifier: Intended Audience :: Developers
Classifier: Intended Audience :: Education
Classifier: Topic :: Scientific/Engineering
Classifier: Topic :: Scientific/Engineering :: GIS
Classifier: License :: OSI Approved :: BSD License
Classifier: Programming Language :: Python
Classifier: Programming Language :: Python :: 3.8
Classifier: Programming Language :: Python :: 3.9
Classifier: Programming Language :: Python :: 3.10
License-File: LICENSE.txt
Requires-Dist: scipy (>=1.0)
Requires-Dist: numpy (>=1.3)
Requires-Dist: scikit-learn
Requires-Dist: pandas (>=1.0)
Requires-Dist: networkx
Provides-Extra: docs
Requires-Dist: sphinx (>=1.4.3) ; extra == 'docs'
Requires-Dist: sphinx-gallery ; extra == 'docs'
Requires-Dist: sphinxcontrib-bibtex ; extra == 'docs'
Requires-Dist: sphinx-bootstrap-theme ; extra == 'docs'
Requires-Dist: numpydoc ; extra == 'docs'
Provides-Extra: speedups
Requires-Dist: numba ; extra == 'speedups'
Provides-Extra: tests
Requires-Dist: pytest ; extra == 'tests'
Requires-Dist: pytest-cov ; extra == 'tests'
Requires-Dist: pytest-xdist ; extra == 'tests'
Requires-Dist: codecov ; extra == 'tests'
Requires-Dist: geopandas ; extra == 'tests'
Requires-Dist: libpysal ; extra == 'tests'
Requires-Dist: networkx ; extra == 'tests'
Requires-Dist: palettable ; extra == 'tests'
